ape_turnkey/__init__.py
ape_turnkey/_cli.py
ape_turnkey/accounts.py
ape_turnkey/client.py
ape_turnkey/exceptions.py
ape_turnkey/py.typed
ape_turnkey/version.py
ape_turnkey-0.8.0a0.dist-info/LICENSE
ape_turnkey-0.8.0a0.dist-info/METADATA
ape_turnkey-0.8.0a0.dist-info/WHEEL
ape_turnkey-0.8.0a0.dist-info/entry_points.txt
ape_turnkey-0.8.0a0.dist-info/top_level.txt
ape_turnkey-0.8.0a0.dist-info/RECORD
