Metadata-Version: 2.1
Name: ape-turnkey
Version: 0.8.0a0
Summary: ape-turnkey: turnkey.com plugin for Ape
Home-page: https://github.com/ApeWorX/ape-turnkey
Author: ApeWorX Ltd.
Author-email: admin@apeworx.io
License: Apache-2.0
Keywords: ethereum
Classifier: Development Status :: 5 - Production/Stable
Classifier: Intended Audience :: Developers
Classifier: License :: OSI Approved :: Apache Software License
Classifier: Natural Language :: English
Classifier: Operating System :: MacOS
Classifier: Operating System :: POSIX
Classifier: Programming Language :: Python :: 3
Classifier: Programming Language :: Python :: 3.9
Classifier: Programming Language :: Python :: 3.10
Classifier: Programming Language :: Python :: 3.11
Classifier: Programming Language :: Python :: 3.12
Classifier: Programming Language :: Python :: 3.13
Requires-Python: >=3.9,<4
License-File: LICENSE
Requires-Dist: cryptography<45,>=44.0
Requires-Dist: eth-ape<0.9,>=0.8
Provides-Extra: dev
Requires-Dist: pytest; extra == "dev"
Requires-Dist: pytest-xdist; extra == "dev"
Requires-Dist: pytest-cov; extra == "dev"
Requires-Dist: hypothesis<7,>=6.2; extra == "dev"
Requires-Dist: black>=25; extra == "dev"
Requires-Dist: mypy>=1.13; extra == "dev"
Requires-Dist: types-setuptools; extra == "dev"
Requires-Dist: types-requests; extra == "dev"
Requires-Dist: flake8>=7.1; extra == "dev"
Requires-Dist: flake8-breakpoint>=1.1; extra == "dev"
Requires-Dist: flake8-print>=5; extra == "dev"
Requires-Dist: flake8-pydantic; extra == "dev"
Requires-Dist: flake8-type-checking; extra == "dev"
Requires-Dist: isort>=5.13; extra == "dev"
Requires-Dist: mdformat>=0.7.19; extra == "dev"
Requires-Dist: mdformat-gfm>=0.3.5; extra == "dev"
Requires-Dist: mdformat-frontmatter>=0.4; extra == "dev"
Requires-Dist: mdformat-pyproject>=0.0.2; extra == "dev"
Requires-Dist: setuptools; extra == "dev"
Requires-Dist: wheel; extra == "dev"
Requires-Dist: twine; extra == "dev"
Requires-Dist: commitizen; extra == "dev"
Requires-Dist: pre-commit; extra == "dev"
Requires-Dist: pytest-watch; extra == "dev"
Requires-Dist: IPython; extra == "dev"
Requires-Dist: ipdb; extra == "dev"
Provides-Extra: lint
Requires-Dist: black>=25; extra == "lint"
Requires-Dist: mypy>=1.13; extra == "lint"
Requires-Dist: types-setuptools; extra == "lint"
Requires-Dist: types-requests; extra == "lint"
Requires-Dist: flake8>=7.1; extra == "lint"
Requires-Dist: flake8-breakpoint>=1.1; extra == "lint"
Requires-Dist: flake8-print>=5; extra == "lint"
Requires-Dist: flake8-pydantic; extra == "lint"
Requires-Dist: flake8-type-checking; extra == "lint"
Requires-Dist: isort>=5.13; extra == "lint"
Requires-Dist: mdformat>=0.7.19; extra == "lint"
Requires-Dist: mdformat-gfm>=0.3.5; extra == "lint"
Requires-Dist: mdformat-frontmatter>=0.4; extra == "lint"
Requires-Dist: mdformat-pyproject>=0.0.2; extra == "lint"
Provides-Extra: release
Requires-Dist: setuptools; extra == "release"
Requires-Dist: wheel; extra == "release"
Requires-Dist: twine; extra == "release"
Provides-Extra: test
Requires-Dist: pytest; extra == "test"
Requires-Dist: pytest-xdist; extra == "test"
Requires-Dist: pytest-cov; extra == "test"
Requires-Dist: hypothesis<7,>=6.2; extra == "test"
